[
  {
    "id": "peugeot208_1",
    "titulo": "Peugeot 208 Feline",
    "marca": "Peugeot",
    "modelo": "208",
    "anio": 2019,
    "estado": "Usado",
    "combustible": "Nafta",
    "transmision": "Manual",
    "color": "Blanco",
    "imagen": "img/peugeot208.jpg",
    "link_ml": "https://auto.mercadolibre.com.ar/MLA-2552727158-peugeot-208-16-feline-_JM",
    "link_wa": "https://wa.me/5491149919122"
  },
  {
    "id": "vpeugeot2008_1",
    "titulo": "Peugeot 2008 Feline Tip",
    "marca": "Peugeot",
    "modelo": "2008",
    "anio": 2018,
    "estado": "Usado",
    "combustible": "Nafta",
    "transmision": "Automática",
    "color": "Negro",
    "imagen": "img/peugeot2008.png",
    "link_ml": "https://auto.mercadolibre.com.ar/MLA-123456789-volkswagen-polo",
    "link_wa": "https://wa.me/5491149919122"
  },
  {
    "id": "vwpolo_2",
    "titulo": "Volkswagen Polo Trendline",
    "marca": "Volkswagen",
    "modelo": "Polo",
    "anio": 2022,
    "estado": "Usado",
    "combustible": "Nafta",
    "transmision": "Manual",
    "color": "Gris",
    "imagen": "img/vw-polo.jpeg",
    "link_ml": "https://auto.mercadolibre.com.ar/MLA-987654321",
    "link_wa": "https://wa.me/5491149919122"
  },
   {
    "id": "peugeot208_1",
    "titulo": "Peugeot 208 Feline",
    "marca": "Peugeot",
    "modelo": "208",
    "anio": 2019,
    "estado": "Usado",
    "combustible": "Nafta",
    "transmision": "Manual",
    "color": "Blanco",
    "imagen": "img/peugeot208.jpg",
    "link_ml": "https://auto.mercadolibre.com.ar/MLA-2552727158-peugeot-208-16-feline-_JM",
    "link_wa": "https://wa.me/5491149919122"
  },
  {
    "id": "vwpolo_1",
    "titulo": "Volkswagen Polo Highline",
    "marca": "Volkswagen",
    "modelo": "Polo",
    "anio": 2023,
    "estado": "Usado",
    "combustible": "Nafta",
    "transmision": "Automática",
    "color": "Azul",
    "imagen": "img/vw-polo.jpeg",
    "link_ml": "https://auto.mercadolibre.com.ar/MLA-123456789-volkswagen-polo",
    "link_wa": "https://wa.me/5491149919122"
  },
  {
    "id": "vwpolo_2",
    "titulo": "Volkswagen Polo Trendline",
    "marca": "Volkswagen",
    "modelo": "Polo",
    "anio": 2022,
    "estado": "Usado",
    "combustible": "Nafta",
    "transmision": "Manual",
    "color": "Gris",
    "imagen": "img/vw-polo.jpeg",
    "link_ml": "https://auto.mercadolibre.com.ar/MLA-987654321",
    "link_wa": "https://wa.me/5491149919122"
  },
   {
    "id": "peugeot208_1",
    "titulo": "Peugeot 208 Feline",
    "marca": "Peugeot",
    "modelo": "208",
    "anio": 2019,
    "estado": "Usado",
    "combustible": "Nafta",
    "transmision": "Manual",
    "color": "Blanco",
    "imagen": "img/peugeot208.jpg",
    "link_ml": "https://auto.mercadolibre.com.ar/MLA-2552727158-peugeot-208-16-feline-_JM",
    "link_wa": "https://wa.me/5491149919122"
  },
  {
    "id": "vwpolo_1",
    "titulo": "Volkswagen Polo Highline",
    "marca": "Volkswagen",
    "modelo": "Polo",
    "anio": 2023,
    "estado": "Usado",
    "combustible": "Nafta",
    "transmision": "Automática",
    "color": "Azul",
    "imagen": "img/vw-polo.jpeg",
    "link_ml": "https://auto.mercadolibre.com.ar/MLA-123456789-volkswagen-polo",
    "link_wa": "https://wa.me/5491149919122"
  },
  {
    "id": "vwpolo_2",
    "titulo": "Volkswagen Polo Trendline",
    "marca": "Volkswagen",
    "modelo": "Polo",
    "anio": 2022,
    "estado": "Usado",
    "combustible": "Nafta",
    "transmision": "Manual",
    "color": "Gris",
    "imagen": "img/vw-polo.jpeg",
    "link_ml": "https://auto.mercadolibre.com.ar/MLA-987654321",
    "link_wa": "https://wa.me/5491149919122"
  }


]